asyncffmpeg/__init__.py
asyncffmpeg/exceptions.py
asyncffmpeg/ffmpeg_coroutine.py
asyncffmpeg/ffmpeg_coroutine_factory.py
asyncffmpeg/py.typed
asyncffmpeg/type_alias.py
asyncffmpeg/ffmpegprocess/__init__.py
asyncffmpeg/ffmpegprocess/interface.py
asyncffmpeg/ffmpegprocess/posix.py
asyncffmpeg/ffmpegprocess/windows.py
asyncffmpeg/ffmpegprocess/windows_wrapper.py
asyncffmpeg/pipe/__init__.py
asyncffmpeg/pipe/pipe_manager.py
asyncffmpeg/pipe/realtime_pipe_reader.py
asyncffmpeg-1.2.0.dist-info/LICENSE
asyncffmpeg-1.2.0.dist-info/METADATA
asyncffmpeg-1.2.0.dist-info/WHEEL
asyncffmpeg-1.2.0.dist-info/top_level.txt
asyncffmpeg-1.2.0.dist-info/RECORD
